bibiinstaller/__init__.py
bibiinstaller/bibiinstaller_configs.py
bibiinstaller/bibiinstaller_windows.py
bibiinstaller/bibiinstaller_windows.yaml
bibiinstaller/assets/Windows/README.md
bibiinstaller/assets/Windows/exes/bibiinstaller_app.exe
bibiinstaller/assets/Windows/exes/config.ini
bibiinstaller/assets/Windows/icon_configs/ResourceHacker.exe
bibiinstaller/assets/Windows/icon_configs/ResourceHacker.ini
bibiinstaller/assets/Windows/icon_configs/commands.txt
bibiinstaller/assets/Windows/micromamba/micromamba-1.5.7-win-64.exe
bibiinstaller/assets/Windows/mirrors/.condarc
bibiinstaller/assets/Windows/mirrors/.mambarc
bibiinstaller/assets/Windows/mirrors/pip.ini
bibiinstaller/assets/Windows/nsis/nsis-3.10-win.zip
bibiinstaller/assets/Windows/nsis/Plugins/x86-unicode/WinShell.dll
bibiinstaller/nsi_templates/application.nsi
bibiinstaller/nsi_templates/bibiinstaller.nsi
bibiinstaller/nsi_templates/spyder.nsi
bibiinstaller/nsi_templates/test_nsi_templates.py
bibiinstaller/package_configs/add_packages.txt
bibiinstaller/package_configs/editable_packages.txt
bibiinstaller/package_configs/extra_packages.txt
bibiinstaller/package_configs/skip_packages.txt
bibiinstaller/package_configs/unwanted_packages.txt
bibiinstaller-0.1.4.dist-info/LICENSE.txt
bibiinstaller-0.1.4.dist-info/METADATA
bibiinstaller-0.1.4.dist-info/WHEEL
bibiinstaller-0.1.4.dist-info/entry_points.txt
bibiinstaller-0.1.4.dist-info/top_level.txt
bibiinstaller-0.1.4.dist-info/RECORD
