Metadata-Version: 2.2
Name: bibiinstaller
Version: 0.1.4
Summary: Bibi Installer using pynsist for Windows
Home-page: https://github.com/bibiparrot/bibiinstaller
Author: Chunqi Shi
Author-email: Chunqi SHI <chunqishi@gmail.com>
License: MIT
Project-URL: Homepage, https://github.com/bibiparrot/bibiinstaller
Project-URL: Issues, https://github.com/bibiparrot/bibiinstaller/issues
Classifier: Programming Language :: Python :: 3
Classifier: License :: OSI Approved :: MIT License
Classifier: Operating System :: OS Independent
Requires-Python: >=3.10
License-File: LICENSE.txt
Requires-Dist: loguru>=0.7.2
Requires-Dist: bibiflags>=0.1.5
Requires-Dist: packaging>=24.0
Requires-Dist: tomli>=2.0.1
Requires-Dist: pillow>=10.3.0
Dynamic: author
Dynamic: home-page
